LICENSE
MANIFEST.in
README.md
remote_networks.csv
requirements.txt
sample.yaml
setup.py
prisma_access_sase.egg-info/PKG-INFO
prisma_access_sase.egg-info/SOURCES.txt
prisma_access_sase.egg-info/dependency_links.txt
prisma_access_sase.egg-info/entry_points.txt
prisma_access_sase.egg-info/requires.txt
prisma_access_sase.egg-info/top_level.txt
prismasase/__init__.py
prismasase/__main__.py
prismasase/_version.py
prismasase/configs.py
prismasase/exceptions.py
prismasase/restapi.py
prismasase/statics.py
prismasase/utilities.py
prismasase/cert_mgmt/__init__.py
prismasase/cert_mgmt/cert_profiles.py
prismasase/cert_mgmt/certs.py
prismasase/cert_mgmt/ocspr.py
prismasase/cert_mgmt/scep.py
prismasase/cert_mgmt/tls.py
prismasase/cert_mgmt/trusted_certs.py
prismasase/config_mgmt/__init__.py
prismasase/config_mgmt/configuration.py
prismasase/identity_svcs/__init__.py
prismasase/policy_objects/__init__.py
prismasase/policy_objects/address_grps.py
prismasase/policy_objects/addresses.py
prismasase/policy_objects/app_filters.py
prismasase/policy_objects/app_override.py
prismasase/policy_objects/apps.py
prismasase/policy_objects/autotags.py
prismasase/policy_objects/dynamic_usr_grp.py
prismasase/policy_objects/hip_obj.py
prismasase/policy_objects/hip_prof.py
prismasase/policy_objects/quarentined_devices.py
prismasase/policy_objects/regions.py
prismasase/policy_objects/schedules.py
prismasase/policy_objects/svc_grps.py
prismasase/policy_objects/svcs.py
prismasase/policy_objects/tags.py
prismasase/policy_objects/url_cat.py
prismasase/policy_objects/url_filt_cat.py
prismasase/sec_services/__init__.py
prismasase/security_svcs/__init__.py
prismasase/service_setup/__init__.py
prismasase/service_setup/service_connections.py
prismasase/service_setup/ike/__init__.py
prismasase/service_setup/ike/ike_crypto.py
prismasase/service_setup/ike/ike_gtwy.py
prismasase/service_setup/ipsec/__init__.py
prismasase/service_setup/ipsec/ipsec_crypto.py
prismasase/service_setup/ipsec/ipsec_tun.py
prismasase/service_setup/remotenetworks/__init__.py
prismasase/service_setup/remotenetworks/remote_networks.py