Metadata-Version: 2.1
Name: prisma-access-sase
Version: 0.2.5
Summary: UNKNOWN
Home-page: https://github.com/atav928/prisma-access-sase
Author: atav928
Author-email: adam@tavnets.com
Maintainer-email: adam@tavnets.com
License: UNKNOWN
Keywords: sase,prisma access,prisma,paloalto
Platform: UNKNOWN
